colour_model/__init__.py
colour_model-0.0.1.dist-info/METADATA
colour_model-0.0.1.dist-info/WHEEL
colour_model-0.0.1.dist-info/top_level.txt
colour_model-0.0.1.dist-info/RECORD
