Metadata-Version: 2.1
Name: colour-model
Version: 0.0.1
Summary: My first Python package
Author: George Pearse
